pickmeup/PickMeUp.py
pickmeup/__init__.py
pickmeup/tests/__init__.py
pickmeup/tests/tests.py
pickmeup-0.0.3.dist-info/METADATA
pickmeup-0.0.3.dist-info/WHEEL
pickmeup-0.0.3.dist-info/licenses/LICENSE
pickmeup-0.0.3.dist-info/RECORD
