Metadata-Version: 2.1
Name: pickmeup
Version: 0.0.3
Summary: Pick up failed list processing without re-processing
Project-URL: Homepage, https://github.com/timgarrels/PickMeUp
Project-URL: Bug Tracker, https://github.com/timgarrels/PickMeUp/issues
Project-URL: Repository, https://github.com/timgarrels/PickMeUp
Author-email: Tim Garrels <tim.garrels@protonmail.com>
License-File: LICENSE
Classifier: License :: OSI Approved :: MIT License
Classifier: Operating System :: OS Independent
Classifier: Programming Language :: Python :: 3
Requires-Python: >=3.7
